columnjump/__init__.py
columnjump/columnjump.py
columnjump/columnjump_step.py
columnjump/jwstpipe1p1p0_ramp_fit.py
columnjump/jwstpipe1p1p0_utils.py
columnjump/rampbreaks.py
columnjump-1.1.1.dist-info/licenses/LICENSE
columnjump-1.1.1.dist-info/METADATA
columnjump-1.1.1.dist-info/WHEEL
columnjump-1.1.1.dist-info/top_level.txt
columnjump-1.1.1.dist-info/RECORD
