Metadata-Version: 2.4
Name: columnjump
Version: 1.1.1
Summary: Fix column jumps for JWST NIRISS detector
Home-page: https://github.com/chriswillott/jwst/columnjump
Author: Chris Willott
Author-email: chriswillott1@gmail.com
Classifier: Programming Language :: Python :: 3
Classifier: License :: OSI Approved :: MIT License
Classifier: Operating System :: OS Independent
Requires-Python: >=3.6
License-File: LICENSE
Dynamic: author
Dynamic: author-email
Dynamic: classifier
Dynamic: description
Dynamic: description-content-type
Dynamic: home-page
Dynamic: license-file
Dynamic: requires-python
Dynamic: summary
